source_kyriba/__init__.py
source_kyriba/run.py
source_kyriba/schemas/accounts.json
source_kyriba/schemas/bank_balances_eod.json
source_kyriba/schemas/bank_balances_intraday.json
source_kyriba/schemas/cash_balances_eod.json
source_kyriba/schemas/cash_balances_intraday.json
source_kyriba/schemas/cash_flows.json
source_kyriba/schemas/shared/_definitions.json
source_kyriba/source.py
source_kyriba/spec.json
airbyte_source_kyriba-0.1.59.dist-info/METADATA
airbyte_source_kyriba-0.1.59.dist-info/WHEEL
airbyte_source_kyriba-0.1.59.dist-info/entry_points.txt
airbyte_source_kyriba-0.1.59.dist-info/RECORD
